package/__init__.py
package/main.py
fbchese-1.0.0.dist-info/METADATA
fbchese-1.0.0.dist-info/WHEEL
fbchese-1.0.0.dist-info/top_level.txt
fbchese-1.0.0.dist-info/RECORD
